pyramid_creator/__init__.py
pyramid_creator/__main__.py
pyramid_creator/pyramid_creator.py
pyramid_creator/scripts/createPyramids.groovy
pyramid_creator-2024.12.18.1.dist-info/METADATA
pyramid_creator-2024.12.18.1.dist-info/WHEEL
pyramid_creator-2024.12.18.1.dist-info/entry_points.txt
pyramid_creator-2024.12.18.1.dist-info/licenses/LICENSE
pyramid_creator-2024.12.18.1.dist-info/RECORD
