Metadata-Version: 2.4
Name: pyramid-creator
Version: 2024.12.18.1
Summary: Create pyramidal OME-TIFF from regular OME-TIFF images using QuPath or Python backend.
Project-URL: Homepage, https://github.com/TeamNCMC/pyramid-creator
Project-URL: Source Code, https://github.com/TeamNCMC/pyramid-creator
Project-URL: Bug Tracker, https://github.com/TeamNCMC/pyramid-creator/issues
Author-email: Guillaume Le Goc <g.legoc@posteo.org>
License: MIT
License-File: LICENSE
Classifier: Programming Language :: Python :: 3.12
Requires-Python: >=3.12
Requires-Dist: tqdm
Requires-Dist: typer
Provides-Extra: python-backend
Requires-Dist: numpy>=2; extra == 'python-backend'
Requires-Dist: scikit-image>0.22.0; extra == 'python-backend'
Requires-Dist: tifffile[codecs]>=2024.4.24; extra == 'python-backend'
